chacha20_utils/__init__.py
chacha20_utils/chacha20_utils.py
chacha20_utils-0.1.1.dist-info/LICENSE
chacha20_utils-0.1.1.dist-info/METADATA
chacha20_utils-0.1.1.dist-info/WHEEL
chacha20_utils-0.1.1.dist-info/top_level.txt
chacha20_utils-0.1.1.dist-info/RECORD
