Metadata-Version: 2.2
Name: chacha20_utils
Version: 0.1.1
Summary: A simple ChaCha20 encryption/decryption utility.
Home-page: https://github.com/SAKIB-SALIM/chacha20-utils
Author: Sakib Salim
Author-email: salimsakib775@yahoo.com
Classifier: Programming Language :: Python :: 3
Classifier: License :: OSI Approved :: MIT License
Classifier: Operating System :: OS Independent
Requires-Python: >=3.6
License-File: LICENSE
Requires-Dist: cryptography
Dynamic: author
Dynamic: author-email
Dynamic: classifier
Dynamic: description
Dynamic: description-content-type
Dynamic: home-page
Dynamic: requires-dist
Dynamic: requires-python
Dynamic: summary
